scala_option/__init__.py
scala_option/exceptions.py
scala_option/none_option.py
scala_option/option.py
scala_option/some_option.py
scala_option-1.0.2.dist-info/LICENSE
scala_option-1.0.2.dist-info/METADATA
scala_option-1.0.2.dist-info/WHEEL
scala_option-1.0.2.dist-info/top_level.txt
scala_option-1.0.2.dist-info/RECORD
