Metadata-Version: 2.2
Name: scala-option
Version: 1.0.2
Summary: Scala like Option type in Python
Author-email: Alex Suopanki <alex.suopanki@gmail.com>
License: MIT
Project-URL: Repository, https://github.com/Suopunki/scala-option
Keywords: option,optional,maybe,functional
Classifier: Intended Audience :: Developers
Classifier: License :: OSI Approved :: MIT License
Classifier: Operating System :: OS Independent
Classifier: Programming Language :: Python :: 3 :: Only
Classifier: Topic :: Software Development :: Libraries
Requires-Python: >=3.12
License-File: LICENSE
Provides-Extra: dev
Requires-Dist: pytest; extra == "dev"
Requires-Dist: pytest-cov; extra == "dev"
